{"createdAt":"2025-06-13T01:24:41.818Z","updatedAt":"2025-06-13T17:27:47.280Z","id":"JTK1fBk9UFFKX6g2","name":"RSS CONTENT OBTAINER","active":true,"isArchived":false,"nodes":[{"parameters":{"pollTimes":{"item":[{"mode":"everyMinute"}]},"feedUrl":"https://artificialintelligence-news.com/feed/"},"type":"n8n-nodes-base.rssFeedReadTrigger","typeVersion":1,"position":[-80,-160],"id":"eed39e44-e14b-4cd5-b0a3-03c171bf061f","name":"RSS Feed Trigger"},{"parameters":{"pollTimes":{"item":[{"mode":"everyMinute"}]},"feedUrl":"https://artificialintelligence-news.com/feed/"},"type":"n8n-nodes-base.rssFeedReadTrigger","typeVersion":1,"position":[480,480],"id":"b1adb72c-3ab7-45d4-b25f-f59eca077fef","name":"RSS Feed Trigger5"},{"parameters":{"pollTimes":{"item":[{"mode":"everyMinute"}]},"feedUrl":"https://artificialintelligence-news.com/feed/"},"type":"n8n-nodes-base.rssFeedReadTrigger","typeVersion":1,"position":[360,360],"id":"5e467188-d34e-4001-9e63-9b10ba7570d0","name":"RSS Feed Trigger4"},{"parameters":{"pollTimes":{"item":[{"mode":"everyMinute"}]},"feedUrl":"https://artificialintelligence-news.com/feed/"},"type":"n8n-nodes-base.rssFeedReadTrigger","typeVersion":1,"position":[240,240],"id":"974b48b8-8042-4874-9475-52b777007a0b","name":"RSS Feed Trigger3"},{"parameters":{"pollTimes":{"item":[{"mode":"everyMinute"}]},"feedUrl":"https://artificialintelligence-news.com/feed/"},"type":"n8n-nodes-base.rssFeedReadTrigger","typeVersion":1,"position":[120,120],"id":"c530d946-2abe-4ae4-bc64-26082bc87964","name":"RSS Feed Trigger2"},{"parameters":{"pollTimes":{"item":[{"mode":"everyMinute"}]},"feedUrl":"https://artificialintelligence-news.com/feed/"},"type":"n8n-nodes-base.rssFeedReadTrigger","typeVersion":1,"position":[20,-20],"id":"f8281a30-7cab-4c38-87d9-5d7a54201c64","name":"RSS Feed Trigger1"},{"parameters":{"workflowId":{"__rl":true,"value":"GRBO0XGoeKW62Lfm","mode":"list","cachedResultName":"Instagram media creation"},"workflowInputs":{"mappingMode":"defineBelow","value":{},"matchingColumns":[],"schema":[],"attemptToConvertTypes":false,"convertFieldsToString":true},"options":{"waitForSubWorkflow":true}},"type":"n8n-nodes-base.executeWorkflow","typeVersion":1.2,"position":[220,-160],"id":"9eaa78ff-aaf8-4be4-86f5-6fafc717f05e","name":"Execute Workflow"}],"connections":{"RSS Feed Trigger":{"main":[[{"node":"Execute Workflow","type":"main","index":0}]]}},"settings":{"executionOrder":"v1"},"staticData":{"node:RSS Feed Trigger":{"lastItemDate":"2025-06-13T13:34:08.000Z"},"node:RSS Feed Trigger5":{"lastItemDate":"2025-06-13T13:34:08.000Z"},"node:RSS Feed Trigger4":{"lastItemDate":"2025-07-02T16:01:40.000Z"},"node:RSS Feed Trigger3":{"lastItemDate":"2025-07-02T16:01:40.000Z"},"node:RSS Feed Trigger2":{"lastItemDate":"2025-07-02T16:01:40.000Z"},"node:RSS Feed Trigger1":{"lastItemDate":"2025-07-02T16:01:40.000Z"}},"meta":null,"pinData":{},"versionId":"fcfbe368-4420-45b9-b27a-842cae9d6154","triggerCount":6,"tags":[],"repo":{"owner":"veridianbr","name":"backup","path":"workflows/"}}